ironbook_sdk/__init__.py
ironbook_sdk/client.py
ironbook_sdk/types.py
ironbook_sdk-0.3.3.dist-info/licenses/LICENSE
ironbook_sdk-0.3.3.dist-info/METADATA
ironbook_sdk-0.3.3.dist-info/WHEEL
ironbook_sdk-0.3.3.dist-info/top_level.txt
ironbook_sdk-0.3.3.dist-info/RECORD
