Metadata-Version: 2.4
Name: ironbook-sdk
Version: 0.3.3
Summary: Python SDK for Iron Book by Identity Machines
Author-email: Identity Machines <devops@identitymachines.com>
License-Expression: MIT
Project-URL: Homepage, https://www.identitymachines.com
Project-URL: Repository, https://github.com/identitymachines/ironbook-sdk-python
Project-URL: Documentation, https://docs.identitymachines.com
Classifier: Development Status :: 3 - Alpha
Classifier: Intended Audience :: Developers
Classifier: Programming Language :: Python :: 3
Classifier: Programming Language :: Python :: 3.8
Classifier: Programming Language :: Python :: 3.9
Classifier: Programming Language :: Python :: 3.10
Classifier: Programming Language :: Python :: 3.11
Classifier: Programming Language :: Python :: 3.12
Requires-Python: >=3.8
License-File: LICENSE
Requires-Dist: httpx>=0.24.0
Dynamic: license-file
